{
    "easy": [
                {"nor":"王", "diff":"土"},
                {"nor":"天", "diff":"夫"},
                {"nor":"于", "diff":"干"},
                {"nor":"土", "diff":"干"},
                {"nor":"鸟", "diff":"乌"},
                {"nor":"乌", "diff":"鸟"},
                {"nor":"人", "diff":"入"},
                {"nor":"甲", "diff":"申"},
                {"nor":"申", "diff":"甲"},
                {"nor":"未", "diff":"末"},
                {"nor":"生", "diff":"生"},
                {"nor":"牛", "diff":"牛"},
                {"nor":"矿", "diff":"旷"},
                {"nor":"方", "diff":"万"},
                {"nor":"沼", "diff":"招"},
                {"nor":"土", "diff":"士"},
                {"nor":"幻", "diff":"幼"},
                {"nor":"幸", "diff":"辛"},
                {"nor":"慢", "diff":"漫"},
                {"nor":"译", "diff":"择"},
                {"nor":"晒", "diff":"洒"},
                {"nor":"旷", "diff":"扩"}
             ],
    "med": [
                {"nor":"乒", "diff":"乓"},
                {"nor":"纪", "diff":"记"},
                {"nor":"茶", "diff":"荼"},
                {"nor":"律", "diff":"津"},
                {"nor":"本", "diff":"木"},
                {"nor":"往", "diff":"住"},
                {"nor":"季", "diff":"李"},
                {"nor":"斗", "diff":"头"},
                {"nor":"平", "diff":"乎"},
                {"nor":"组", "diff":"租"},
                {"nor":"珠", "diff":"殊"},
                {"nor":"玲", "diff":"铃"},
                {"nor":"坏", "diff":"环"},
                {"nor":"杜", "diff":"社"},
                {"nor":"沙", "diff":"纱"},
                {"nor":"风", "diff":"凤"},
                {"nor":"欺", "diff":"斯"},
                {"nor":"斥", "diff":"斤"},
                {"nor":"明", "diff":"朋"},
                {"nor":"赶", "diff":"起"},
                {"nor":"看", "diff":"着"},
                {"nor":"吗", "diff":"妈"},
                {"nor":"免", "diff":"兔"},
                {"nor":"爷", "diff":"斧"},
                {"nor":"耍", "diff":"要"},
                {"nor":"究", "diff":"穷"},
                {"nor":"促", "diff":"捉"},
                {"nor":"异", "diff":"导"},
                {"nor":"壮", "diff":"状"},
                {"nor":"综", "diff":"踪"},
                {"nor":"钓", "diff":"钩"},
                {"nor":"钩", "diff":"构"},
                {"nor":"钩", "diff":"豹"},
                {"nor":"铁", "diff":"跌"},
                {"nor":"胆", "diff":"担"},
                {"nor":"治", "diff":"冶"},
                {"nor":"牵", "diff":"牢"},
                {"nor":"勾", "diff":"勺"},
                {"nor":"予", "diff":"矛"},
                {"nor":"呜", "diff":"鸣"},
                {"nor":"蛮", "diff":"恋"},
                {"nor":"充", "diff":"允"},
                {"nor":"预", "diff":"舒"},
                {"nor":"稍", "diff":"销"},
                {"nor":"哀", "diff":"衰"},
                {"nor":"挂", "diff":"桂"},
                {"nor":"拳", "diff":"卷"},
                {"nor":"价", "diff":"阶"},
                {"nor":"铺", "diff":"辅"},
                {"nor":"责", "diff":"青"}
           ]
}